JekPost-2.1.0.dist-info/DESCRIPTION.rst
JekPost-2.1.0.dist-info/METADATA
JekPost-2.1.0.dist-info/RECORD
JekPost-2.1.0.dist-info/WHEEL
JekPost-2.1.0.dist-info/entry_points.txt
JekPost-2.1.0.dist-info/metadata.json
JekPost-2.1.0.dist-info/top_level.txt
jekpost/__init__.py
jekpost/jekpost.py
jekpost/jekpost_create.py
